<properties xmlns="http://schemas.sulu.io/template/template"
            xmlns:xsi="http://www.w3.org/2001/XMLSchema-instance"
            xsi:schemaLocation="http://schemas.sulu.io/template/template http://schemas.sulu.io/template/template-1.0.xsd">
    <block name="blocks" default-type="quote">
        <!-- @see https://docs.sulu.io/en/2.1/reference/content-types/block.html -->

        <types>
            <type name="quote">
                <meta>
                    <title lang="en">Quote</title>
                    <title lang="de">Zitat</title>
                </meta>

                <properties>
                    <property name="quote" type="text_area" mandatory="true">
                        <meta>
                            <title lang="en">Quote</title>
                            <title lang="de">Zitat</title>
                        </meta>
                    </property>

                    <property name="quoteReference" type="text_line">
                        <meta>
                            <title lang="en">Reference</title>
                            <title lang="de">Referenz</title>
                        </meta>
                    </property>
                </properties>
            </type>
        </types>
    </block>
</properties>
